puma/__init__.py
puma/fraction_scan.py
puma/histogram.py
puma/integrated_eff.py
puma/line_plot_2d.py
puma/matshow.py
puma/pie.py
puma/plot_base.py
puma/roc.py
puma/var_vs_eff.py
puma/var_vs_var.py
puma/var_vs_vtx.py
puma/hlplots/__init__.py
puma/hlplots/aux_results.py
puma/hlplots/n_track_origin.py
puma/hlplots/results.py
puma/hlplots/tagger.py
puma/hlplots/yuma.py
puma/hlplots/yutils.py
puma/tests/__init__.py
puma/tests/test_histogram.py
puma/tests/test_integrated_eff.py
puma/tests/test_line_2d.py
puma/tests/test_matshow.py
puma/tests/test_pie_chart.py
puma/tests/test_plot_base.py
puma/tests/test_roc.py
puma/tests/test_truth_hadron.py
puma/tests/test_var_vs_eff.py
puma/tests/test_var_vs_var.py
puma/tests/test_var_vs_vtx.py
puma/tests/hlplots/__init__.py
puma/tests/hlplots/test_aux_results.py
puma/tests/hlplots/test_n_track_origin.py
puma/tests/hlplots/test_results.py
puma/tests/hlplots/test_tagger.py
puma/tests/hlplots/test_yuma.py
puma/tests/utils/__init__.py
puma/tests/utils/test_confusion_matrix.py
puma/tests/utils/test_generate.py
puma/tests/utils/test_histogram_utils.py
puma/tests/utils/test_logging.py
puma/tests/utils/test_mass.py
puma/tests/utils/test_precision_recall.py
puma/tests/utils/test_utils.py
puma/tests/utils/test_vertexing.py
puma/utils/__init__.py
puma/utils/aux.py
puma/utils/confusion_matrix.py
puma/utils/generate.py
puma/utils/histogram.py
puma/utils/logger.py
puma/utils/mass.py
puma/utils/precision_recall_scores.py
puma/utils/truth_hadron.py
puma/utils/vertexing.py
puma_hep-0.4.12.dist-info/licenses/LICENSE
puma_hep-0.4.12.dist-info/METADATA
puma_hep-0.4.12.dist-info/WHEEL
puma_hep-0.4.12.dist-info/entry_points.txt
puma_hep-0.4.12.dist-info/top_level.txt
puma_hep-0.4.12.dist-info/RECORD
