Metadata-Version: 2.4
Name: puma-hep
Version: 0.4.12
Summary: ATLAS Flavour Tagging Plotting - Plotting Umami API (PUMA)
Home-page: https://github.com/umami-hep/puma
Author: Joschka Birk, Alexander Froch, Manuel Guth
License: MIT
Project-URL: Homepage, https://github.com/umami-hep/puma
Project-URL: Issue Tracker, https://github.com/umami-hep/puma/issues
Requires-Python: <3.12,>=3.10
License-File: LICENSE
Requires-Dist: atlas-ftag-tools==0.2.17
Requires-Dist: atlasify>=0.8.0
Requires-Dist: h5py>=3.14.0
Requires-Dist: ipython>=8.37.0
Requires-Dist: matplotlib>=3.10.6
Requires-Dist: numpy>=2.2.6
Requires-Dist: palettable>=3.3.0
Requires-Dist: pandas>=2.3.2
Requires-Dist: pydot>=4.0.1
Requires-Dist: pyyaml-include==1.3
Requires-Dist: scipy>=1.15.3
Requires-Dist: tables>=3.10.1
Requires-Dist: testfixtures>=8.3.0
Provides-Extra: dev
Requires-Dist: coverage>=7.10.6; extra == "dev"
Requires-Dist: ipykernel>=6.30.1; extra == "dev"
Requires-Dist: mypy>=1.18.1; extra == "dev"
Requires-Dist: pre-commit>=4.3.0; extra == "dev"
Requires-Dist: pydoclint>=0.7.3; extra == "dev"
Requires-Dist: pytest_notebook>=0.10.0; extra == "dev"
Requires-Dist: pytest-cov>=7.0.0; extra == "dev"
Requires-Dist: pytest-randomly>=4.0.1; extra == "dev"
Requires-Dist: pytest>=8.4.2; extra == "dev"
Requires-Dist: ruff>=0.13.0; extra == "dev"
Dynamic: license-file
